LICENSE.txt
README.md
setup.cfg
setup.py
scikit_weak/__init__.py
scikit_weak.egg-info/PKG-INFO
scikit_weak.egg-info/SOURCES.txt
scikit_weak.egg-info/dependency_links.txt
scikit_weak.egg-info/requires.txt
scikit_weak.egg-info/top_level.txt
scikit_weak/classification/__init__.py
scikit_weak/classification/_ensemble.py
scikit_weak/classification/_grm.py
scikit_weak/classification/_neighbors.py
scikit_weak/classification/_pseudolabels.py
scikit_weak/classification/_relaxation.py
scikit_weak/data_representation/__init__.py
scikit_weak/data_representation/_representations.py
scikit_weak/feature_selection/__init__.py
scikit_weak/feature_selection/_delin.py
scikit_weak/feature_selection/_geneticroughset.py
scikit_weak/feature_selection/_roughset.py
scikit_weak/tests/__init__.py
scikit_weak/tests/classification/__init__.py
scikit_weak/tests/classification/test_grm.py
scikit_weak/tests/classification/test_neighbors.py
scikit_weak/tests/classification/test_pseudolabels.py
scikit_weak/tests/classification/test_relaxation.py
scikit_weak/tests/data_representation/__init__.py
scikit_weak/tests/data_representation/test_representations.py
scikit_weak/tests/feature_selection/__init__.py
scikit_weak/tests/feature_selection/test_geneticroughset.py
scikit_weak/tests/feature_selection/test_roughset.py
scikit_weak/tests/utils/__init__.py
scikit_weak/tests/utils/test_smoothers.py
scikit_weak/utils/__init__.py
scikit_weak/utils/_losses.py
scikit_weak/utils/_smoothers.py
scikit_weak/utils/_utils.py