Metadata-Version: 2.1
Name: scikit-weak
Version: 0.2.1
Summary: A package featuring utilities and algorithms for weakly supervised ML.
Home-page: https://pypi.org/project/scikit-weak/
Author: Andrea Campagner
Author-email: a.campagner@campus.unimib.it
License: LICENSE.txt
Platform: UNKNOWN
Requires-Python: >3.8.0
License-File: LICENSE.txt
